permissions_management/__init__.py
permissions_management/admin.py
permissions_management/apps.py
permissions_management/conftest.py
permissions_management/constants.py
permissions_management/factories.py
permissions_management/models.py
permissions_management/tests.py
permissions_management/utils.py
permissions_management/views.py
permissions_management/api/__init__.py
permissions_management/api/pagination.py
permissions_management/api/permissions.py
permissions_management/api/serializers.py
permissions_management/api/urls.py
permissions_management/api/views.py
permissions_management/migrations/__init__.py
troo_permission_management-1.0.dist-info/LICENSE
troo_permission_management-1.0.dist-info/METADATA
troo_permission_management-1.0.dist-info/WHEEL
troo_permission_management-1.0.dist-info/top_level.txt
troo_permission_management-1.0.dist-info/RECORD
